{
  "nodos": [
    {
      "id": 1,
      "label": "q0",
      "x": 150,
      "y": 150,
      "esInicial": true,
      "esFinal": false,
      "transiciones": [
        {
          "id": "trans-1",
          "simboloLee": "a",
          "simboloEscribe": "a",
          "movimiento": "R",
          "proximoEstado": 1
        },
        {
          "id": "trans-2",
          "simboloLee": "b",
          "simboloEscribe": "b",
          "movimiento": "R",
          "proximoEstado": 2
        }
      ]
    },
    {
      "id": 2,
      "label": "q1",
      "x": 350,
      "y": 150,
      "esInicial": false,
      "esFinal": false,
      "transiciones": [
        {
          "id": "trans-3",
          "simboloLee": "b",
          "simboloEscribe": "b",
          "movimiento": "R",
          "proximoEstado": 2
        }
      ]
    },
    {
      "id": 3,
      "label": "q2",
      "x": 550,
      "y": 150,
      "esInicial": false,
      "esFinal": true,
      "transiciones": []
    }
  ],
  "conexiones": [
    {
      "id": "conn-0",
      "origenId": 1,
      "destinoId": 1,
      "controlPoints": [
        {
          "x": 200,
          "y": 50
        }
      ]
    },
    {
      "id": "conn-1",
      "origenId": 1,
      "destinoId": 2,
      "controlPoints": [
        {
          "x": 250,
          "y": 100
        }
      ]
    },
    {
      "id": "conn-2",
      "origenId": 2,
      "destinoId": 2,
      "controlPoints": [
        {
          "x": 400,
          "y": 50
        }
      ]
    },
    {
      "id": "conn-3",
      "origenId": 2,
      "destinoId": 3,
      "controlPoints": [
        {
          "x": 450,
          "y": 100
        }
      ]
    }
  ]
}
